stream_sea_client/__init__.py
stream_sea_client/api.py
stream_sea_client/stream_sea_connection.py
stream_sea_client/stream_sea_schema_definition.py
stream_sea_client-0.1.0.dist-info/METADATA
stream_sea_client-0.1.0.dist-info/WHEEL
stream_sea_client-0.1.0.dist-info/top_level.txt
stream_sea_client-0.1.0.dist-info/RECORD
